mcp_kintone_lite/client.py
mcp_kintone_lite/server.py
mcp_kintone_lite/tools/__init__.py
mcp_kintone_lite/tools/crud_tools.py
mcp_kintone_lite/tools/metadata_tools.py
mcp_kintone_lite/tools/query_tools.py
mcp_kintone_lite-0.1.0.dist-info/LICENSE
mcp_kintone_lite-0.1.0.dist-info/METADATA
mcp_kintone_lite-0.1.0.dist-info/WHEEL
mcp_kintone_lite-0.1.0.dist-info/entry_points.txt
mcp_kintone_lite-0.1.0.dist-info/RECORD
