Metadata-Version: 2.3
Name: mcp-kintone-lite
Version: 0.1.0
Summary: Simple and lightweight Kintone MCP server for connecting AI assistants to Kintone applications and data
License: MIT
Keywords: kintone,mcp,ai,assistant,workflow,automation
Author: Your Name
Author-email: your.email@example.com
Requires-Python: >=3.10
Classifier: Development Status :: 4 - Beta
Classifier: Intended Audience :: Developers
Classifier: License :: OSI Approved :: MIT License
Classifier: Programming Language :: Python :: 3
Classifier: Programming Language :: Python :: 3.10
Classifier: Programming Language :: Python :: 3.11
Classifier: Programming Language :: Python :: 3.12
Classifier: Topic :: Software Development :: Libraries :: Python Modules
Classifier: Topic :: Office/Business
Classifier: Topic :: Internet :: WWW/HTTP :: Dynamic Content
Requires-Dist: mcp (>=1.0.0)
Requires-Dist: python-dotenv (>=1.0.0)
Requires-Dist: requests (>=2.31.0)
Project-URL: Homepage, https://github.com/yourusername/mcp-kintone-lite
Project-URL: Issues, https://github.com/yourusername/mcp-kintone-lite/issues
Project-URL: Repository, https://github.com/yourusername/mcp-kintone-lite
